eoddata/__init__.py
eoddata/accounting.py
eoddata/client.py
eoddata/exceptions.py
eoddata/api/__init__.py
eoddata/api/base.py
eoddata/api/corporate.py
eoddata/api/exchanges.py
eoddata/api/fundamentals.py
eoddata/api/metadata.py
eoddata/api/quotes.py
eoddata/api/symbols.py
eoddata/api/technicals.py
eoddata_api-0.1.0.dist-info/licenses/LICENSE
eoddata_api-0.1.0.dist-info/METADATA
eoddata_api-0.1.0.dist-info/WHEEL
eoddata_api-0.1.0.dist-info/top_level.txt
eoddata_api-0.1.0.dist-info/RECORD
