Metadata-Version: 2.4
Name: eoddata-api
Version: 0.1.0
Summary: Python client package for the EODData market data REST API.
Home-page: https://github.com/vrontier/eoddata
Author: Mike Quest
Author-email: Mike Quest <eoddata-api@vrontier.org>
License: MIT License
Project-URL: Homepage, https://github.com/vrontier/eoddata-api
Project-URL: Repository, https://github.com/vrontier/eoddata-api
Project-URL: Issues, https://github.com/vrontier/eoddata-api/issues
Keywords: finance,markets,eod,historical-data,api,stocks,eoddata
Classifier: Intended Audience :: Developers
Classifier: Intended Audience :: Financial and Insurance Industry
Classifier: License :: OSI Approved :: MIT License
Classifier: Operating System :: OS Independent
Classifier: Programming Language :: Python :: 3
Classifier: Programming Language :: Python :: 3.10
Classifier: Programming Language :: Python :: 3.11
Classifier: Programming Language :: Python :: 3.12
Classifier: Programming Language :: Python :: 3.13
Classifier: Topic :: Office/Business :: Financial
Classifier: Topic :: Software Development :: Libraries :: Python Modules
Requires-Python: >=3.10
License-File: LICENSE
Requires-Dist: requests<3,>=2.32.0
Provides-Extra: dev
Requires-Dist: pytest>=6.0; extra == "dev"
Requires-Dist: pytest-cov; extra == "dev"
Requires-Dist: pytest-mock; extra == "dev"
Requires-Dist: black; extra == "dev"
Requires-Dist: flake8; extra == "dev"
Requires-Dist: mypy; extra == "dev"
Dynamic: author
Dynamic: home-page
Dynamic: license-file
Dynamic: requires-python
